<?xml version="1.0" encoding="ISO-8859-1"?>

<bugs>
	<bug>
		<id>77</id>
		<title> Exception java.lang.NullPointerException:</title>
		<body>https://console.firebase.google.com/project/ai-la-trieu-phu-online/monitoring/app/android:com.game.oic.ailatrieuphu/cluster/65e6dfca?duration=2592000000 </body>
		<created>2016-10-16 04:06:47</created>
		<closed>2016-10-17 12:01:44</closed>
	</bug>
	<bug>
		<id>76</id>
		<title>Exception java.lang.NullPointerException:</title>
		<body>https://console.firebase.google.com/project/ai-la-trieu-phu-online/monitoring/app/android:com.game.oic.ailatrieuphu/cluster/65e6dfca?duration=2592000000 </body>
		<created>2016-10-16 04:06:23</created>
		<closed>2016-10-17 12:01:51</closed>
	</bug>
	<bug>
		<id>75</id>
		<title>Exception java.lang.SecurityException</title>
		<body>https://console.firebase.google.com/project/ai-la-trieu-phu-online/monitoring/app/android:com.game.oic.ailatrieuphu/cluster/84cd4ed4?duration=2592000000 </body>
		<created>2016-10-16 04:05:27</created>
		<closed>2016-10-17 12:01:36</closed>
	</bug>
</bugs>
