<?xml version="1.0" encoding="ISO-8859-1"?>

<bugs>
	<bug>
		<id>116</id>
		<title>Terasology no buildea</title>
		<body>Al ejecutar "./gradlew build" en terasology este falla, segun lo que marca el error se debe a modo fly  ![image](https://cloud.githubusercontent.com/assets/10638887/9216944/93f501d4-4097-11e5-9e08-dce78e1d9598.png) </body>
		<created>2015-08-12 05:13:14</created>
		<closed>2015-08-12 13:32:49</closed>
	</bug>
	<bug>
		<id>102</id>
		<title>Fallo de funcionamiento</title>
		<body>Terasology dejo de funcionar después de commit https://github.com/Ciclop/Terasology/commit/129ecd87441733d2a2b063bb929e214d8b40e926 </body>
		<created>2015-07-29 15:55:16</created>
		<closed>2015-07-29 20:13:41</closed>
	</bug>
	<bug>
		<id>95</id>
		<title>Problema al hacer run de terasology</title>
		<body>Mientras hacia merge de mi rama me di cuenta que anteriormente el juego no se ejecutaba, es decir, al realizar el tipico proceso de build, compileJava y run todo funcionaba pero al crear una partida se queda pegado mientras carga con el mensaje "Awaiting Character Spawn...", creo que deben revisar cual es el commit que hizo eso y arreglarlo para seguir trabajando normalmente en el master.  PD: Uso Ubuntu y tengo java 8 </body>
		<created>2015-05-26 19:32:17</created>
		<closed>2015-05-28 04:44:34</closed>
	</bug>
</bugs>
