<?xml version="1.0" encoding="ISO-8859-1"?>

<pullrequests>
	<pullrequest>
		<number>1940</number>
		<title>closes #1939 - remove google places api e add CET places api</title>
		<body>closes #1939 - remove google places api e add CTE places api</body>
		<to>1939</to>
	</pullrequest>
	<pullrequest>
		<number>1933</number>
		<title>fix entrada manual somente apos final do ciclo primeiro anel</title>
		<body>close #1928 </body>
		<to>1928</to>
	</pullrequest>
	<pullrequest>
		<number>1932</number>
		<title>closes #1921 - limite de falhas registradas por intervalo de tempo</title>
		<body>closes #1921 </body>
		<to>1921</to>
	</pullrequest>
	<pullrequest>
		<number>1931</number>
		<title>1929 imposicao sob imposicao</title>
		<body>close #1929 </body>
		<to>1929</to>
	</pullrequest>
	<pullrequest>
		<number>1919</number>
		<title>1908 melhoria comandos central</title>
		<body>close #1908  close #1907  close #1913  close #1915 </body>
		<to>1908</to>
	</pullrequest>
	<pullrequest>
		<number>1917</number>
		<title>Fix erro criar evento em agrupamento</title>
		<body>fixes #1916</body>
		<to>1916</to>
	</pullrequest>
	<pullrequest>
		<number>1911</number>
		<title>1898 ajustes validacao controlador</title>
		<body>close #1898  close #1819 </body>
		<to>1898</to>
	</pullrequest>
	<pullrequest>
		<number>1906</number>
		<title>Cadastrar eventos de agrupamento</title>
		<body>fixes #1896</body>
		<to>1896</to>
	</pullrequest>
	<pullrequest>
		<number>1904</number>
		<title>fix mensagens botoes footer</title>
		<body>close #1899 </body>
		<to>1899</to>
	</pullrequest>
	<pullrequest>
		<number>1903</number>
		<title>1894 ajustes manual com demanda prioritaria</title>
		<body>close #1894  close #1901  close #1902 </body>
		<to>1894</to>
	</pullrequest>
	<pullrequest>
		<number>1888</number>
		<title>add verde de seguranca</title>
		<body>close #1880 </body>
		<to>1880</to>
	</pullrequest>
	<pullrequest>
		<number>1886</number>
		<title>add endereco controlador no simulador</title>
		<body>close #1877 </body>
		<to>1877</to>
	</pullrequest>
	<pullrequest>
		<number>1885</number>
		<title>1876 estagio dispensavel</title>
		<body>close #1871 close #1876 close #1870 </body>
		<to>1871</to>
	</pullrequest>
	<pullrequest>
		<number>1881</number>
		<title>Travamento iniciar simulador :bomb:</title>
		<body>close #1866 </body>
		<to>1866</to>
	</pullrequest>
	<pullrequest>
		<number>1863</number>
		<title>Filtro controladores por online/offline</title>
		<body>fixes #1857</body>
		<to>1857</to>
	</pullrequest>
	<pullrequest>
		<number>1861</number>
		<title>1852 ler dados</title>
		<body>fixes #1852 </body>
		<to>1852</to>
	</pullrequest>
	<pullrequest>
		<number>1860</number>
		<title>1854 sequencia partida grupo semaforico</title>
		<body>close #1854 </body>
		<to>1854</to>
	</pullrequest>
	<pullrequest>
		<number>1848</number>
		<title>Erro manual em falha</title>
		<body>close #1847 </body>
		<to>1847</to>
	</pullrequest>
	<pullrequest>
		<number>1845</number>
		<title>fix entrada modo apagado</title>
		<body>close #1843 </body>
		<to>1843</to>
	</pullrequest>
	<pullrequest>
		<number>1844</number>
		<title>Fix erro endereço controlador</title>
		<body>fixes #1827</body>
		<to>1827</to>
	</pullrequest>
	<pullrequest>
		<number>1842</number>
		<title>1838 erro entrada manual</title>
		<body>close #1838 </body>
		<to>1838</to>
	</pullrequest>
	<pullrequest>
		<number>1837</number>
		<title>Fix relatório planos</title>
		<body>fixes #1833</body>
		<to>1833</to>
	</pullrequest>
	<pullrequest>
		<number>1836</number>
		<title>1834 coordenacao aneis</title>
		<body>close #1834 </body>
		<to>1834</to>
	</pullrequest>
	<pullrequest>
		<number>1832</number>
		<title>fix acionamento durante estagio com estagio dispensavel duplo</title>
		<body>close #1828 close #1835  </body>
		<to>1828</to>
	</pullrequest>
	<pullrequest>
		<number>1831</number>
		<title>add tempo de ciclo duplo</title>
		<body>close #1796   @JuarezLustosa rodar o cucumber e criar novos para esse novo cenário</body>
		<to>1796</to>
	</pullrequest>
	<pullrequest>
		<number>1816</number>
		<title>Link do dashboard p/ comandos da central</title>
		<body>fixes #1812</body>
		<to>1812</to>
	</pullrequest>
	<pullrequest>
		<number>1814</number>
		<title>ajuste atraso de grupo</title>
		<body>close #1810 </body>
		<to>1810</to>
	</pullrequest>
	<pullrequest>
		<number>1809</number>
		<title>add verificacao de isDestroy nas validacao de plano</title>
		<body>close #1807  @JuarezLustosa roda o cucumber</body>
		<to>1807</to>
	</pullrequest>
	<pullrequest>
		<number>1803</number>
		<title>add validacao de ciclo assimetrico e simetrico</title>
		<body>close #1798 </body>
		<to>1798</to>
	</pullrequest>
	<pullrequest>
		<number>1792</number>
		<title>Permissões simulação e dashboard</title>
		<body>close #1789  close #1790 </body>
		<to>1789</to>
	</pullrequest>
	<pullrequest>
		<number>1784</number>
		<title>1730 status dashboard</title>
		<body>closes #1730 - Status dinâmicos em dashboard e mapa.</body>
		<to>1730</to>
	</pullrequest>
	<pullrequest>
		<number>1757</number>
		<title>Ajustes planos</title>
		<body>close #1715  close #1731  close #1732  close #1710 </body>
		<to>1715</to>
	</pullrequest>
	<pullrequest>
		<number>1754</number>
		<title>1587 atraso por diferenca entreverde</title>
		<body>close #1587 </body>
		<to>1587</to>
	</pullrequest>
	<pullrequest>
		<number>1752</number>
		<title>Perfil obrigatório para usuários se não for root</title>
		<body>fixes #1706</body>
		<to>1706</to>
	</pullrequest>
	<pullrequest>
		<number>1749</number>
		<title>Fix validação plano + fix mensagem erro plano</title>
		<body>fixes #1721 fixes #1713</body>
		<to>1721</to>
	</pullrequest>
	<pullrequest>
		<number>1746</number>
		<title>1712 erro validacao manual</title>
		<body>close #1712 </body>
		<to>1712</to>
	</pullrequest>
	<pullrequest>
		<number>1743</number>
		<title>1718 erro dois estagio dispensavel</title>
		<body>close #1718 </body>
		<to>1718</to>
	</pullrequest>
	<pullrequest>
		<number>1742</number>
		<title>Fix paginação relatórios</title>
		<body>fixes #1711</body>
		<to>1711</to>
	</pullrequest>
	<pullrequest>
		<number>1739</number>
		<title>1724 grupo semaforico apagado simulador</title>
		<body>close #1724</body>
		<to>1724</to>
	</pullrequest>
	<pullrequest>
		<number>1734</number>
		<title>fix cancelar edicao controlador</title>
		<body>close #825 </body>
		<to>825</to>
	</pullrequest>
	<pullrequest>
		<number>1704</number>
		<title>Troca status "ativo" p/ "sincronizado" no index de controladores</title>
		<body>fixes #1693</body>
		<to>1693</to>
	</pullrequest>
	<pullrequest>
		<number>1703</number>
		<title>tempo maximo plano isolado</title>
		<body>close #1700 </body>
		<to>1700</to>
	</pullrequest>
	<pullrequest>
		<number>1702</number>
		<title>ajustes ordenação + correção relatorio log + ajuste blockUI</title>
		<body>fixes #1696 fixes #1684 fixes #1674</body>
		<to>1696</to>
	</pullrequest>
	<pullrequest>
		<number>1701</number>
		<title>verifica verde seguranca primeiro estagio do plano</title>
		<body>close #1652 </body>
		<to>1652</to>
	</pullrequest>
	<pullrequest>
		<number>1698</number>
		<title>add saida da imposicao na tela</title>
		<body>close #1685 </body>
		<to>1685</to>
	</pullrequest>
	<pullrequest>
		<number>1683</number>
		<title>Hotfix log controlador</title>
		<body>close #1672  close #1673 </body>
		<to>1672</to>
	</pullrequest>
	<pullrequest>
		<number>1682</number>
		<title>remover os planos manuais da validacao de existir em todos os aneis</title>
		<body>close #1681 </body>
		<to>1681</to>
	</pullrequest>
	<pullrequest>
		<number>1671</number>
		<title>Ajuste marcacao de erro em estagio planos</title>
		<body>close #1670   @pauloFernandes, @ppires favor validar esse PR @JuarezLustosa roda o cucumber em cima desse PR, se passar vamos colocar ele em staging e depois atualizar os servidores staging e production</body>
		<to>1670</to>
	</pullrequest>
	<pullrequest>
		<number>1665</number>
		<title>Ajustes finais</title>
		<body>close #1658  close #1656  close #1659 </body>
		<to>1658</to>
	</pullrequest>
	<pullrequest>
		<number>1661</number>
		<title>closes #1653</title>
		<body>closes #1653 -&gt; Valida que todos os aneis tenham os mesmos planos ativados (exceto para os planos temporários).</body>
		<to>1653</to>
	</pullrequest>
	<pullrequest>
		<number>1660</number>
		<title>Ajustes arquivo de configuração do controlador</title>
		<body>fixes #1655</body>
		<to>1655</to>
	</pullrequest>
	<pullrequest>
		<number>1650</number>
		<title>closes #1646</title>
		<body>closes #1646 -&gt; limpar mensagens de validação quando o usuário alterar dados no plano</body>
		<to>1646</to>
	</pullrequest>
	<pullrequest>
		<number>1648</number>
		<title>1645 ajustar modo operacao simulador</title>
		<body>closes #1573 -&gt; alteração de labels do sistema. closes #1645 -&gt; troca de label do modo de operação no simulador.</body>
		<to>1573</to>
	</pullrequest>
	<pullrequest>
		<number>1641</number>
		<title>Melhoria mensagem de nova versão plano e tabela horária</title>
		<body>fixes #1633</body>
		<to>1633</to>
	</pullrequest>
	<pullrequest>
		<number>1638</number>
		<title>Download de arquivo de configuração do controlador</title>
		<body>fixes #1617</body>
		<to>1617</to>
	</pullrequest>
	<pullrequest>
		<number>1637</number>
		<title>Permissões painel de facilidades</title>
		<body>fixes #1603</body>
		<to>1603</to>
	</pullrequest>
	<pullrequest>
		<number>1636</number>
		<title>ajustes status dashboard</title>
		<body>close #1629 </body>
		<to>1629</to>
	</pullrequest>
	<pullrequest>
		<number>1635</number>
		<title>1571 salvar log troca plano</title>
		<body>close #1571</body>
		<to>1571</to>
	</pullrequest>
	<pullrequest>
		<number>1634</number>
		<title>Fix busca por falha em relatório de falhas</title>
		<body>fixes #1561</body>
		<to>1561</to>
	</pullrequest>
	<pullrequest>
		<number>1630</number>
		<title>1542 controladores teste</title>
		<body>closes #1542 - Criação da flag de controlador para testes</body>
		<to>1542</to>
	</pullrequest>
	<pullrequest>
		<number>1626</number>
		<title>ajuste alarmes controlador</title>
		<body>close #1564 </body>
		<to>1564</to>
	</pullrequest>
	<pullrequest>
		<number>1625</number>
		<title>1562 painel facilidades controlador offline</title>
		<body>close #1562 </body>
		<to>1562</to>
	</pullrequest>
	<pullrequest>
		<number>1622</number>
		<title>enviar dados do hardware</title>
		<body>close #1520 </body>
		<to>1520</to>
	</pullrequest>
	<pullrequest>
		<number>1618</number>
		<title>Ajustes textos</title>
		<body>close #1582  close #1568  close #1569  close #1566  close #1613 </body>
		<to>1582</to>
	</pullrequest>
	<pullrequest>
		<number>1616</number>
		<title>Gerenciar ciclo de vida do simulador</title>
		<body>fixes #1334</body>
		<to>1334</to>
	</pullrequest>
	<pullrequest>
		<number>1612</number>
		<title>add test de leitura de dados</title>
		<body>close #1567 </body>
		<to>1567</to>
	</pullrequest>
	<pullrequest>
		<number>1611</number>
		<title>últimos 30 dias no status do controlador</title>
		<body>fixes #1147</body>
		<to>1147</to>
	</pullrequest>
	<pullrequest>
		<number>1610</number>
		<title>1586 imposicao modo varios aneis</title>
		<body>close #1586 </body>
		<to>1586</to>
	</pullrequest>
	<pullrequest>
		<number>1608</number>
		<title>Fix validação plano</title>
		<body>fixes #1584</body>
		<to>1584</to>
	</pullrequest>
	<pullrequest>
		<number>1607</number>
		<title>Fix relatório controlador PDF</title>
		<body>fixes #1593  </body>
		<to>1593</to>
	</pullrequest>
	<pullrequest>
		<number>1605</number>
		<title>unificar inicioSimulacao e inicioControlador e remover fimSimulacao</title>
		<body>close #1576  close #1585 </body>
		<to>1576</to>
	</pullrequest>
	<pullrequest>
		<number>1601</number>
		<title>fixes #1589</title>
		<body>fixes #1589 </body>
		<to>1589</to>
	</pullrequest>
	<pullrequest>
		<number>1556</number>
		<title>fixes endereço 2 validação sem altura numérica</title>
		<body>closes #1481 </body>
		<to>1481</to>
	</pullrequest>
	<pullrequest>
		<number>1555</number>
		<title>ler dados do controlador</title>
		<body>close #1502 </body>
		<to>1502</to>
	</pullrequest>
	<pullrequest>
		<number>1552</number>
		<title>1515 ajustar monitoramente estagio</title>
		<body>close #1515</body>
		<to>1515</to>
	</pullrequest>
	<pullrequest>
		<number>1538</number>
		<title>Breadcrumb endereço controlador em tabela horária</title>
		<body>closes #1511 </body>
		<to>1511</to>
	</pullrequest>
	<pullrequest>
		<number>1536</number>
		<title>Fix bug ao limpar plano temporário</title>
		<body>closes #1521 bug ao limpar plano temporário </body>
		<to>1521</to>
	</pullrequest>
	<pullrequest>
		<number>1528</number>
		<title>validacao tempo de verde demanda prioritaria</title>
		<body>close #1512 </body>
		<to>1512</to>
	</pullrequest>
	<pullrequest>
		<number>1527</number>
		<title>Tempo verde seguranca</title>
		<body>close #1504 </body>
		<to>1504</to>
	</pullrequest>
	<pullrequest>
		<number>1524</number>
		<title>1506 - Imposição de plano temporário</title>
		<body>fixes #1506</body>
		<to>1506</to>
	</pullrequest>
	<pullrequest>
		<number>1523</number>
		<title>1492 desarme alarmes bkp</title>
		<body>closes #1492  </body>
		<to>1492</to>
	</pullrequest>
	<pullrequest>
		<number>1507</number>
		<title>1305 relatorio logs</title>
		<body>fix #1305</body>
		<to>1305</to>
	</pullrequest>
	<pullrequest>
		<number>1505</number>
		<title>Validação transição proibida com destino demanda prioritária</title>
		<body>fixes #1499   Se um estágio de demanda prioritária for destino de uma transição proibida, o estágio de origem não pode ser o estágio alternativo. </body>
		<to>1499</to>
	</pullrequest>
	<pullrequest>
		<number>1491</number>
		<title>1333 impor configuracao</title>
		<body>closes #1333 imposições e sincronizações.</body>
		<to>1333</to>
	</pullrequest>
	<pullrequest>
		<number>1469</number>
		<title>relatorio de planos</title>
		<body>fix #1308 </body>
		<to>1308</to>
	</pullrequest>
	<pullrequest>
		<number>1464</number>
		<title>fix mensagem erro ciclo em agrupamento</title>
		<body>close #1428   @JuarezLustosa criar um cucumber que testa isso.</body>
		<to>1428</to>
	</pullrequest>
	<pullrequest>
		<number>1463</number>
		<title>1436 modo manual simulador</title>
		<body>close #1445  close #1439 close #1438  </body>
		<to>1445</to>
	</pullrequest>
	<pullrequest>
		<number>1462</number>
		<title>imprimir revisao</title>
		<body>fix #1174</body>
		<to>1174</to>
	</pullrequest>
	<pullrequest>
		<number>1458</number>
		<title>relatorio de falhas</title>
		<body>fix #1306 </body>
		<to>1306</to>
	</pullrequest>
	<pullrequest>
		<number>1449</number>
		<title>closes #865 - finalizar sessao por tempo de inatividade</title>
		<body>closes #865 - finalizar sessao por tempo de inatividade</body>
		<to>865</to>
	</pullrequest>
	<pullrequest>
		<number>1416</number>
		<title>1303 alertas e erros</title>
		<body>close #1303</body>
		<to>1303</to>
	</pullrequest>
	<pullrequest>
		<number>1415</number>
		<title>1411 epic de correcoes</title>
		<body>closes #1411 Correções/sugestões do PDF (10/11/2016) </body>
		<to>1411</to>
	</pullrequest>
	<pullrequest>
		<number>1412</number>
		<title>1388 - remover estágios planos</title>
		<body>fixes #1388</body>
		<to>1388</to>
	</pullrequest>
	<pullrequest>
		<number>1402</number>
		<title>fixes #1353</title>
		<body>fixes #1353 Erro ao excluir um fabricante com modelo associado a um controlador.</body>
		<to>1353</to>
	</pullrequest>
	<pullrequest>
		<number>1400</number>
		<title>fixes #1377</title>
		<body>fixes #1377: Todos os aneis que aceitam plano manual exclusivo deverão ter o este plano configurado, se a quantidade de aneis no controlador for maior que 1.  Altera também o comportamento anterior da lista de planos: Se o usuário troca do `anel 1` para `anel 2` estando no `plano 2`, o `plano 2` estaria selecionado no `anel 2` e seria colocado como `configurado` automaticamente. Isto somente deverá ocorrer se o `plano 2` em `anel 1` estiver configurado.</body>
		<to>1377</to>
	</pullrequest>
	<pullrequest>
		<number>1398</number>
		<title>1396 - hotfix estagios planos</title>
		<body>fixes #1396</body>
		<to>1396</to>
	</pullrequest>
	<pullrequest>
		<number>1397</number>
		<title>1393 bug transicoes proibidas</title>
		<body>fixes #1393 </body>
		<to>1393</to>
	</pullrequest>
	<pullrequest>
		<number>1384</number>
		<title>remover validacao transicao proibida para estagio de demanda prioritaria</title>
		<body>close #1382 </body>
		<to>1382</to>
	</pullrequest>
	<pullrequest>
		<number>1374</number>
		<title>fix ajustes finos planos</title>
		<body>close #1346  close #1347  </body>
		<to>1346</to>
	</pullrequest>
	<pullrequest>
		<number>1372</number>
		<title>1324 implementar troca planos especiais</title>
		<body>close #1324  close #619  close #1345 </body>
		<to>1324</to>
	</pullrequest>
	<pullrequest>
		<number>1370</number>
		<title>fixes #1355 - bug estágio que recebe tempo do estágio dispensável</title>
		<body>fixes #1355 - bug estágio que recebe tempo do estágio dispensável</body>
		<to>1355</to>
	</pullrequest>
	<pullrequest>
		<number>1369</number>
		<title>1366 epic modelo controlador</title>
		<body>fixes #1366    * fixes #1352    * fixes #1341 </body>
		<to>1366</to>
	</pullrequest>
	<pullrequest>
		<number>1364</number>
		<title>1363 hotfix edicao aneis</title>
		<body>closes #1363 - hotfixes de aneis   * fixes #1340 - Apagar dados dos aneis com problemas   * closes #1361 - Problema não repetido   * fixes #1358 - A tela de grupos semafóricos será somente acessível se houver ao menos dois estágios por anel ativo.</body>
		<to>1363</to>
	</pullrequest>
	<pullrequest>
		<number>1344</number>
		<title>closes #1310 - obrigar SMEE ao finalizar controlador</title>
		<body>closes #1310 - obrigar SMEE ao finalizar controlador</body>
		<to>1310</to>
	</pullrequest>
	<pullrequest>
		<number>1337</number>
		<title>fixes #1329</title>
		<body>fixes #1329 </body>
		<to>1329</to>
	</pullrequest>
	<pullrequest>
		<number>1336</number>
		<title>add calculo de extensao de verde</title>
		<body>close #1298 </body>
		<to>1298</to>
	</pullrequest>
	<pullrequest>
		<number>1327</number>
		<title>fixes #1326 - extensao de verde deve suportar casas decimais</title>
		<body>fixes #1326 -&gt; Extensão de verde em décimos de segundo.</body>
		<to>1326</to>
	</pullrequest>
	<pullrequest>
		<number>1301</number>
		<title>fixes 1246 and fixes #1281</title>
		<body>fixes #1246 -&gt; Remover dados de anel quando for deletado; fixes #1281 -&gt; Remoção das auditorias do menu</body>
		<to>1246</to>
	</pullrequest>
	<pullrequest>
		<number>1297</number>
		<title>Validação número de estágios em plano modo manual</title>
		<body>closes #1258</body>
		<to>1258</to>
	</pullrequest>
	<pullrequest>
		<number>1296</number>
		<title>add validacoes planos</title>
		<body>close #1292 close #1262  close #1257  close #1263  close #1269 </body>
		<to>1292</to>
	</pullrequest>
	<pullrequest>
		<number>1293</number>
		<title>add validacao de tempo de permanencia de estagio</title>
		<body>close #1266 </body>
		<to>1266</to>
	</pullrequest>
	<pullrequest>
		<number>1291</number>
		<title>1264 posicao latlng</title>
		<body>closes #1264 - Alteração da posição dos campos de lat e lng para o final de todas as áreas de endereços.</body>
		<to>1264</to>
	</pullrequest>
	<pullrequest>
		<number>1290</number>
		<title>closes #1264 posicao dos campos de lat lng</title>
		<body>closes #1264 </body>
		<to>1264</to>
	</pullrequest>
	<pullrequest>
		<number>1277</number>
		<title>ajustes campos faixa de valores</title>
		<body>close #1238 </body>
		<to>1238</to>
	</pullrequest>
	<pullrequest>
		<number>1275</number>
		<title>verificar a geracao de intervalos na saida do modo intermitente</title>
		<body>close #1273  </body>
		<to>1273</to>
	</pullrequest>
	<pullrequest>
		<number>1272</number>
		<title>add geracao de intervalo estagio unico</title>
		<body>closes #1251  </body>
		<to>1251</to>
	</pullrequest>
	<pullrequest>
		<number>1229</number>
		<title>closes #1124</title>
		<body>closes #1124: Usabilidade ao editar o controlador. </body>
		<to>1124</to>
	</pullrequest>
	<pullrequest>
		<number>1228</number>
		<title>closes #1161 - Validacao agrupamento - aneis devem ser da mesma area</title>
		<body>closes #1161 - Validacao agrupamento - aneis devem ser da mesma area </body>
		<to>1161</to>
	</pullrequest>
	<pullrequest>
		<number>1225</number>
		<title>closes #1211 - inverter posicao de/para de transicoes proibidas</title>
		<body>closes #1211  - Inverter posição de/para na tabela de transições proibidas (+cucumber ok) </body>
		<to>1211</to>
	</pullrequest>
	<pullrequest>
		<number>1216</number>
		<title>fixes some issues</title>
		<body>fixes #1150 (Mensagem de salvo com sucesso para faixas de valores) fixes #916 (diretiva para botões de footer do wizard + mensagens de salvo com sucesso para salvar e permanecer na tela) </body>
		<to>1150</to>
	</pullrequest>
	<pullrequest>
		<number>1202</number>
		<title>fixes #1193</title>
		<body>fixes #1193   OBS.: O arquivo `influunt-app/app/plugins/roundSlider-1.3/roundslider.js` é um plugin. Considerar somente as linhas 903-906 na revisão. </body>
		<to>1193</to>
	</pullrequest>
	<pullrequest>
		<number>1195</number>
		<title>relatorio de tabelas entreverdes atualizadas no periodo</title>
		<body>close #1185  </body>
		<to>1185</to>
	</pullrequest>
	<pullrequest>
		<number>1192</number>
		<title>1079 teste planos</title>
		<body>fixes #1176  - bug na tabela horária. Possui também o progresso parcial da atualização dos testes de planos e tabelas horárias (+refactors) </body>
		<to>1176</to>
	</pullrequest>
	<pullrequest>
		<number>1191</number>
		<title>1176 hotfix tabela horaria</title>
		<body>fixes #1176   Para isso, este branch carrega algumas alterações feitas nos controllers de planos e tabelas horárias (frontend). </body>
		<to>1176</to>
	</pullrequest>
	<pullrequest>
		<number>1182</number>
		<title>relatorio de controladores por falhas</title>
		<body>close #1171 </body>
		<to>1171</to>
	</pullrequest>
	<pullrequest>
		<number>1170</number>
		<title>relatorio de controladores por status</title>
		<body>close #1167  </body>
		<to>1167</to>
	</pullrequest>
	<pullrequest>
		<number>1164</number>
		<title>1054 relatorio auditoria</title>
		<body>close #1054  </body>
		<to>1054</to>
	</pullrequest>
	<pullrequest>
		<number>1162</number>
		<title>1149 menu cadastro</title>
		<body>fixes #1149 fixes #1155 </body>
		<to>1149</to>
	</pullrequest>
	<pullrequest>
		<number>1129</number>
		<title>fixes #1125</title>
		<body>fixes #1125  </body>
		<to>1125</to>
	</pullrequest>
	<pullrequest>
		<number>1127</number>
		<title>1118 fix dropzone</title>
		<body>fixes #1118  - fixes #1083  - fixes #1099  - Corrige problemas do influunt-dropzone quando a API responde com um código de erro ao app. </body>
		<to>1118</to>
	</pullrequest>
	<pullrequest>
		<number>1119</number>
		<title>fix envio de email</title>
		<body>fix #1114 #1093  </body>
		<to>1114</to>
	</pullrequest>
	<pullrequest>
		<number>1117</number>
		<title>fixes #1102</title>
		<body>fixes #1102 </body>
		<to>1102</to>
	</pullrequest>
	<pullrequest>
		<number>1116</number>
		<title>fixes #1105 :unamused:</title>
		<body>fixes #1105 😒  </body>
		<to>1105</to>
	</pullrequest>
	<pullrequest>
		<number>1111</number>
		<title>fix busca por area</title>
		<body>fix #1098  </body>
		<to>1098</to>
	</pullrequest>
	<pullrequest>
		<number>1109</number>
		<title>1107 view mapa</title>
		<body>fixes #1107  </body>
		<to>1107</to>
	</pullrequest>
	<pullrequest>
		<number>1068</number>
		<title>1066 epic ajustes</title>
		<body>fixes #1066  - fixes #1058  - fixes #1059  - fixes #1061  - Corrige todos os jshints apresentados em `staging` </body>
		<to>1066</to>
	</pullrequest>
	<pullrequest>
		<number>1064</number>
		<title>886 usabilidade planos</title>
		<body>fixes #886 </body>
		<to>886</to>
	</pullrequest>
	<pullrequest>
		<number>1052</number>
		<title>validacao de faixa de valores</title>
		<body>close #1040  </body>
		<to>1040</to>
	</pullrequest>
	<pullrequest>
		<number>1047</number>
		<title>fix tabela horario</title>
		<body>close #1043 </body>
		<to>1043</to>
	</pullrequest>
	<pullrequest>
		<number>1041</number>
		<title>fixes #1027</title>
		<body>fixes #1027   Como o problema acontece em um dos plugins, eu fiz a correção em um arquivo a parte e adicionei este aos plugins. Eu também fiz um PR para o plugin. Se houver resposta do dono, removemos o arquivo que criei e voltamos para o bower. </body>
		<to>1027</to>
	</pullrequest>
	<pullrequest>
		<number>1037</number>
		<title>configurar controle manual</title>
		<body>close #891 </body>
		<to>891</to>
	</pullrequest>
	<pullrequest>
		<number>1036</number>
		<title>fixes #1026 - pesquisa auditorias</title>
		<body>fixes #1026 . </body>
		<to>1026</to>
	</pullrequest>
	<pullrequest>
		<number>1034</number>
		<title>998 cadastro agrupamento</title>
		<body>fixes #998  </body>
		<to>998</to>
	</pullrequest>
	<pullrequest>
		<number>1021</number>
		<title>remover planos e tabelas horarios quando necessario</title>
		<body>close #990  </body>
		<to>990</to>
	</pullrequest>
	<pullrequest>
		<number>1020</number>
		<title>fixes #1004 dados duplicados</title>
		<body>fixes #1004  </body>
		<to>1004</to>
	</pullrequest>
	<pullrequest>
		<number>1010</number>
		<title>revisao dos botoes editar</title>
		<body>close #829 </body>
		<to>829</to>
	</pullrequest>
	<pullrequest>
		<number>1003</number>
		<title>fix filtro de controladores</title>
		<body>close #982  </body>
		<to>982</to>
	</pullrequest>
	<pullrequest>
		<number>1001</number>
		<title>inclusao do sql para a tabela de intervalos</title>
		<body>close #999  </body>
		<to>999</to>
	</pullrequest>
	<pullrequest>
		<number>997</number>
		<title>fix pataquada :disappointed: :bomb:</title>
		<body>close #988  </body>
		<to>988</to>
	</pullrequest>
	<pullrequest>
		<number>987</number>
		<title>972 dashboard estatico</title>
		<body>close #972 </body>
		<to>972</to>
	</pullrequest>
	<pullrequest>
		<number>970</number>
		<title>integrar template de email</title>
		<body>close #965  </body>
		<to>965</to>
	</pullrequest>
	<pullrequest>
		<number>959</number>
		<title>fix filtro de auditoria</title>
		<body>fix #958  </body>
		<to>958</to>
	</pullrequest>
	<pullrequest>
		<number>949</number>
		<title>voltar widgets</title>
		<body>fix #948  </body>
		<to>948</to>
	</pullrequest>
	<pullrequest>
		<number>927</number>
		<title>dashboard</title>
		<body>close #707 </body>
		<to>707</to>
	</pullrequest>
	<pullrequest>
		<number>924</number>
		<title>917 loading issues</title>
		<body>resolves #917  - resolves #863  - resolves #879   - resolves #889   - resolves #878  - resolves #888  </body>
		<to>917</to>
	</pullrequest>
	<pullrequest>
		<number>915</number>
		<title>871 mapa controladores</title>
		<body>resolves #871   As ações dos aneis ainda não estão implementadas. </body>
		<to>871</to>
	</pullrequest>
	<pullrequest>
		<number>897</number>
		<title>867 alteracao senha</title>
		<body>close #867  </body>
		<to>867</to>
	</pullrequest>
	<pullrequest>
		<number>864</number>
		<title>666 log acesso</title>
		<body>close #666 </body>
		<to>666</to>
	</pullrequest>
	<pullrequest>
		<number>824</number>
		<title>279 melhorar pesquisas app</title>
		<body>fixes #279 </body>
		<to>279</to>
	</pullrequest>
	<pullrequest>
		<number>779</number>
		<title>485 auditoria</title>
		<body>close #485 </body>
		<to>485</to>
	</pullrequest>
	<pullrequest>
		<number>778</number>
		<title>736 validar dados detectores</title>
		<body>fixes #736 and some codacy issues </body>
		<to>736</to>
	</pullrequest>
	<pullrequest>
		<number>750</number>
		<title>fix mostrar botao ativar</title>
		<body>close #721  </body>
		<to>721</to>
	</pullrequest>
	<pullrequest>
		<number>717</number>
		<title>cancelar edicao tabela horaria</title>
		<body>close #714  </body>
		<to>714</to>
	</pullrequest>
	<pullrequest>
		<number>693</number>
		<title>remover evento da tabela horaria</title>
		<body>close #685  </body>
		<to>685</to>
	</pullrequest>
	<pullrequest>
		<number>688</number>
		<title>518 refactor versao</title>
		<body>close #518  </body>
		<to>518</to>
	</pullrequest>
	<pullrequest>
		<number>672</number>
		<title>644 remover verdes conflitantes</title>
		<body>fix #644 Remoção de verdes conflitantes no wizard de controladores. </body>
		<to>644</to>
	</pullrequest>
	<pullrequest>
		<number>636</number>
		<title>fix knob</title>
		<body>close #575  </body>
		<to>575</to>
	</pullrequest>
	<pullrequest>
		<number>623</number>
		<title>Ajuste tabela horaria</title>
		<body>close #552  </body>
		<to>552</to>
	</pullrequest>
	<pullrequest>
		<number>608</number>
		<title>Cor diferente para tempos nao utilizados</title>
		<body>closes #574  </body>
		<to>574</to>
	</pullrequest>
	<pullrequest>
		<number>605</number>
		<title>Validar tempo verde seguranca</title>
		<body>fix #509  </body>
		<to>509</to>
	</pullrequest>
	<pullrequest>
		<number>597</number>
		<title>Refactor controlador versao</title>
		<body>close #518  </body>
		<to>518</to>
	</pullrequest>
	<pullrequest>
		<number>528</number>
		<title>link para tela de revisao</title>
		<body>fix #527  </body>
		<to>527</to>
	</pullrequest>
	<pullrequest>
		<number>519</number>
		<title>407 versao controlador</title>
		<body>fix #407  </body>
		<to>407</to>
	</pullrequest>
	<pullrequest>
		<number>517</number>
		<title>Revisao de mensagens de de planos e tabela horarios</title>
		<body>fix #512 #504 #490 #496  </body>
		<to>512</to>
	</pullrequest>
	<pullrequest>
		<number>494</number>
		<title>Adicionar agrupamento no plano - API</title>
		<body>fix #479  </body>
		<to>479</to>
	</pullrequest>
	<pullrequest>
		<number>491</number>
		<title>466 revisar diagram intervalos</title>
		<body>fixes #466  </body>
		<to>466</to>
	</pullrequest>
	<pullrequest>
		<number>476</number>
		<title>verde de segurança</title>
		<body>fix #470  </body>
		<to>470</to>
	</pullrequest>
	<pullrequest>
		<number>471</number>
		<title>Modelagem tabela horario</title>
		<body>fix #457  </body>
		<to>457</to>
	</pullrequest>
	<pullrequest>
		<number>465</number>
		<title>salvar planos</title>
		<body>fix #463  </body>
		<to>463</to>
	</pullrequest>
	<pullrequest>
		<number>456</number>
		<title>fix erro ao criar novo usuario</title>
		<body>fix #453  </body>
		<to>453</to>
	</pullrequest>
	<pullrequest>
		<number>454</number>
		<title>fix layout upload dropzone</title>
		<body>fix #451 #437 #438  </body>
		<to>451</to>
	</pullrequest>
	<pullrequest>
		<number>450</number>
		<title>fix monitoramento de tempo de permanencia de estagio</title>
		<body>fix #440  </body>
		<to>440</to>
	</pullrequest>
	<pullrequest>
		<number>445</number>
		<title>fix associacao de grupo e remover transicoes quando e proibida</title>
		<body>fix #442  </body>
		<to>442</to>
	</pullrequest>
	<pullrequest>
		<number>444</number>
		<title>add validacao de verdes conflitantes durante a associacao</title>
		<body>fix #439 </body>
		<to>439</to>
	</pullrequest>
	<pullrequest>
		<number>421</number>
		<title>Refazer json</title>
		<body>fix #343  </body>
		<to>343</to>
	</pullrequest>
	<pullrequest>
		<number>420</number>
		<title>Ajustar tela planos</title>
		<body>fix #364 #366  </body>
		<to>364</to>
	</pullrequest>
	<pullrequest>
		<number>419</number>
		<title>revisao de cucumber de cadastros simples</title>
		<body>fix #411  </body>
		<to>411</to>
	</pullrequest>
	<pullrequest>
		<number>410</number>
		<title>add percentual knob</title>
		<body>fix #204  </body>
		<to>204</to>
	</pullrequest>
	<pullrequest>
		<number>405</number>
		<title>402 aneis enderecos</title>
		<body>fixes #402 (epic) </body>
		<to>402</to>
	</pullrequest>
	<pullrequest>
		<number>398</number>
		<title>fix dropzone upload area</title>
		<body>fixes #378  </body>
		<to>378</to>
	</pullrequest>
	<pullrequest>
		<number>397</number>
		<title>396 enderecos controlador</title>
		<body>resolve #396  resolve #338  resolve #339  </body>
		<to>396</to>
	</pullrequest>
	<pullrequest>
		<number>386</number>
		<title>configuracao controlador</title>
		<body>resolve #334 e #335 </body>
		<to>334</to>
	</pullrequest>
	<pullrequest>
		<number>383</number>
		<title>Ajuste legenda planos</title>
		<body>fix #365 #308  </body>
		<to>365</to>
	</pullrequest>
	<pullrequest>
		<number>372</number>
		<title>alterar ordem do menu wizard na app</title>
		<body>resolve #346  </body>
		<to>346</to>
	</pullrequest>
	<pullrequest>
		<number>369</number>
		<title>unificar tela de fabricante e modelo de controlador</title>
		<body>resolve #332  </body>
		<to>332</to>
	</pullrequest>
	<pullrequest>
		<number>358</number>
		<title>Remover grupo semaforico e detectores da tela de anel e adicionar criacao de grupo semaforico apos anel</title>
		<body>resolve #353 </body>
		<to>353</to>
	</pullrequest>
	<pullrequest>
		<number>355</number>
		<title>#174 - fix ichecks + fix maps em production</title>
		<body>fixes #174  </body>
		<to>174</to>
	</pullrequest>
	<pullrequest>
		<number>354</number>
		<title>352 labels placeholders etc</title>
		<body>fix #328 #330 #333 #337 #344 #345  </body>
		<to>328</to>
	</pullrequest>
	<pullrequest>
		<number>351</number>
		<title>#312 - fix image upload + delete</title>
		<body>fixes #312  </body>
		<to>312</to>
	</pullrequest>
	<pullrequest>
		<number>348</number>
		<title>314 fix login</title>
		<body>fix #314  </body>
		<to>314</to>
	</pullrequest>
	<pullrequest>
		<number>326</number>
		<title>Tela usuarios</title>
		<body>fix #290  </body>
		<to>290</to>
	</pullrequest>
	<pullrequest>
		<number>320</number>
		<title>fix validacao area</title>
		<body>fix #284  </body>
		<to>284</to>
	</pullrequest>
	<pullrequest>
		<number>316</number>
		<title>fix cadastro de cidade com o mesmo nome</title>
		<body>fix #282  </body>
		<to>282</to>
	</pullrequest>
	<pullrequest>
		<number>313</number>
		<title>311 fix ajustes visuais</title>
		<body>fixes #311 #283 #285 #286 #305  </body>
		<to>311</to>
	</pullrequest>
	<pullrequest>
		<number>300</number>
		<title>#246 - ajustes titulos e labels</title>
		<body>fixes #246  </body>
		<to>246</to>
	</pullrequest>
	<pullrequest>
		<number>295</number>
		<title>fix tela de transicoes proibidas</title>
		<body>fix #243 </body>
		<to>243</to>
	</pullrequest>
	<pullrequest>
		<number>293</number>
		<title>fix tela de verdes conflitantes</title>
		<body>fix #242  </body>
		<to>242</to>
	</pullrequest>
	<pullrequest>
		<number>256</number>
		<title>fix menu wizard</title>
		<body>fix #255  </body>
		<to>255</to>
	</pullrequest>
	<pullrequest>
		<number>251</number>
		<title>implementacao faixa de valores</title>
		<body>close #210  </body>
		<to>210</to>
	</pullrequest>
	<pullrequest>
		<number>250</number>
		<title>verificacao modo isolado</title>
		<body>close #235  </body>
		<to>235</to>
	</pullrequest>
	<pullrequest>
		<number>248</number>
		<title>Implementacao fase vermelha</title>
		<body>close #232  </body>
		<to>232</to>
	</pullrequest>
	<pullrequest>
		<number>239</number>
		<title>Incluir numero em agrupamentos</title>
		<body>close #231  </body>
		<to>231</to>
	</pullrequest>
	<pullrequest>
		<number>230</number>
		<title>130 planos</title>
		<body>resolve #130  </body>
		<to>130</to>
	</pullrequest>
</pullrequests>
